Metadata-Version: 2.1
Name: test-module-teorver
Version: 0.0
Summary: test_module_teorver
Author-email: applepro285@gmail.com
